MANIFEST.in
README.rst
setup.cfg
setup.py
data/default_unbound.example
data/unbound_ec2.conf.example
data/unbound_ec2_script
unbound_ec2/__init__.py
unbound_ec2/config.py
unbound_ec2/invalidator.py
unbound_ec2/lookup.py
unbound_ec2/repeater.py
unbound_ec2/script.py
unbound_ec2/server.py
unbound_ec2.egg-info/PKG-INFO
unbound_ec2.egg-info/SOURCES.txt
unbound_ec2.egg-info/dependency_links.txt
unbound_ec2.egg-info/not-zip-safe
unbound_ec2.egg-info/requires.txt
unbound_ec2.egg-info/top_level.txt