Metadata-Version: 1.1
Name: unbound-ec2
Version: 1.3.0
Summary: Unbound DNS resolver to answer simple DNS queries using EC2 API calls
Home-page: https://github.com/unibet/unbound-ec2
Author: Will Maie, Matthew Hooker, Tom Wanielista, Ilja Bobkevic
Author-email: wcmaier@m.aier.us, mwhooker@gmail.com, tom@simple.com, ilja.bobkevic@unibet.com
License: Apache License 2.0
Download-URL: https://github.com/unibet/unbound-ec2/tarball/1.3.0
Platform: Posix; MacOS X
Classifier: Development Status :: 5 - Production/Stable
Classifier: Intended Audience :: Developers
Classifier: Natural Language :: English
Classifier: License :: OSI Approved :: Apache Software License
Classifier: Programming Language :: Python
Classifier: Programming Language :: Python :: 2.6
Classifier: Programming Language :: Python :: 2.7
